nanohelp/__init__.py
nanohelp/secret.py
nanohelp/wallet.py
nanohelp-0.1.13.dist-info/LICENSE
nanohelp-0.1.13.dist-info/METADATA
nanohelp-0.1.13.dist-info/WHEEL
nanohelp-0.1.13.dist-info/RECORD
